setuptools_zig.py
setuptools_zig-0.2.0.dist-info/LICENSE
setuptools_zig-0.2.0.dist-info/METADATA
setuptools_zig-0.2.0.dist-info/WHEEL
setuptools_zig-0.2.0.dist-info/entry_points.txt
setuptools_zig-0.2.0.dist-info/top_level.txt
setuptools_zig-0.2.0.dist-info/RECORD
