Metadata-Version: 2.1
Name: setuptools-zig
Version: 0.2.0
Summary: A setuptools extension, for building cpython extensions with Zig.
Home-page: https://sourceforge.net/p/setuptools-zig/code/ref/default/
Author-email: a.van.der.neut@ruamel.eu
License: MIT
Classifier: License :: OSI Approved :: MIT License
Classifier: Programming Language :: Python :: 3
Classifier: Programming Language :: Python :: 3 :: Only
Classifier: Programming Language :: Python :: 3.7
Classifier: Programming Language :: Python :: 3.8
Classifier: Programming Language :: Python :: 3.9
Classifier: Programming Language :: Python :: 3.10
Classifier: Programming Language :: Python :: 3.11
Classifier: Programming Language :: Python :: Implementation :: CPython
Requires-Python: >=3
License-File: LICENSE
